CHANGES.md
MANIFEST.in
README.md
pytest.ini
setup.py
tox.ini
elixr/__init__.py
elixr/core.py
elixr/exthook.py
elixr.core.egg-info/PKG-INFO
elixr.core.egg-info/SOURCES.txt
elixr.core.egg-info/dependency_links.txt
elixr.core.egg-info/not-zip-safe
elixr.core.egg-info/requires.txt
elixr.core.egg-info/top_level.txt
elixr/ext/__init__.py