Metadata-Version: 1.0
Name: elixr.core
Version: 0.1
Summary: A python general purpose utility library
Home-page: https://github.com/hkmshb/elixr.core
Author: Abdul-Hakeem Shaibu
Author-email: hkmshb@gmail.com
License: UNKNOWN
Keywords: elixr,hazeltek elixr
Platform: any
